[
	{ "name": "jumpDown1", "x": 408, "y": 14, "width": 16, "height": 32 },
	{ "name": "standDown0", "x": 25, "y": 15, "width": 14, "height": 29 },
	{ "name": "pushDown3", "x": 280, "y": 15, "width": 14, "height": 29 },
	{ "name": "jumpDown2", "x": 471, "y": 16, "width": 18, "height": 26 },
	{ "name": "pushDown2", "x": 216, "y": 19, "width": 14, "height": 27 },
	{ "name": "jumpDown0", "x": 340, "y": 20, "width": 24, "height": 24 },
	{ "name": "pushDown0", "x": 88, "y": 24, "width": 16, "height": 22 },
	{ "name": "pushDown1", "x": 152, "y": 25, "width": 16, "height": 20 },
	{ "name": "standUp0", "x": 25, "y": 79, "width": 14, "height": 29 },
	{ "name": "pushUp1", "x": 152, "y": 80, "width": 16, "height": 28 },
	{ "name": "pushUp2", "x": 216, "y": 80, "width": 16, "height": 28 },
	{ "name": "jumpUp1", "x": 406, "y": 80, "width": 20, "height": 33 },
	{ "name": "pushUp0", "x": 88, "y": 81, "width": 16, "height": 28 },
	{ "name": "jumpUp2", "x": 472, "y": 81, "width": 17, "height": 27 },
	{ "name": "pushUp3", "x": 280, "y": 84, "width": 16, "height": 25 },
	{ "name": "jumpUp0", "x": 342, "y": 85, "width": 20, "height": 23 },
	{ "name": "standRight0", "x": 26, "y": 143, "width": 12, "height": 29 },
	{ "name": "pushRight0", "x": 89, "y": 143, "width": 18, "height": 29 },
	{ "name": "pushRight2", "x": 218, "y": 143, "width": 16, "height": 29 },
	{ "name": "pushRight3", "x": 278, "y": 143, "width": 19, "height": 29 },
	{ "name": "jumpRight1", "x": 409, "y": 143, "width": 17, "height": 34 },
	{ "name": "pushRight1", "x": 150, "y": 144, "width": 21, "height": 28 },
	{ "name": "jumpRight2", "x": 476, "y": 144, "width": 13, "height": 27 },
	{ "name": "jumpRight0", "x": 347, "y": 147, "width": 18, "height": 25 },
	{ "name": "standLeft0", "x": 26, "y": 207, "width": 12, "height": 29 },
	{ "name": "pushLeft0", "x": 85, "y": 207, "width": 18, "height": 29 },
	{ "name": "pushLeft2", "x": 214, "y": 207, "width": 16, "height": 29 },
	{ "name": "pushLeft3", "x": 279, "y": 207, "width": 19, "height": 29 },
	{ "name": "jumpLeft1", "x": 406, "y": 207, "width": 17, "height": 34 },
	{ "name": "pushLeft1", "x": 149, "y": 208, "width": 21, "height": 28 },
	{ "name": "jumpLeft2", "x": 471, "y": 208, "width": 13, "height": 27 },
	{ "name": "jumpLeft0", "x": 339, "y": 211, "width": 18, "height": 25 },
	{ "name": "walkDown1", "x": 88, "y": 271, "width": 15, "height": 30 },
	{ "name": "walkDown2", "x": 153, "y": 271, "width": 15, "height": 30 },
	{ "name": "walkDown4", "x": 281, "y": 271, "width": 15, "height": 30 },
	{ "name": "walkDown5", "x": 344, "y": 271, "width": 15, "height": 30 },
	{ "name": "walkDown0", "x": 24, "y": 272, "width": 14, "height": 29 },
	{ "name": "walkDown3", "x": 218, "y": 272, "width": 14, "height": 29 },
	{ "name": "runDown0", "x": 408, "y": 269, "width": 18, "height": 31 },
	{ "name": "runDown1", "x": 470, "y": 269, "width": 18, "height": 31 },
	{ "name": "runUp0", "x": 406, "y": 333, "width": 18, "height": 31 },
	{ "name": "runUp1", "x": 472, "y": 333, "width": 18, "height": 31 },
	{ "name": "walkUp1", "x": 88, "y": 335, "width": 17, "height": 29 },
	{ "name": "walkUp2", "x": 151, "y": 335, "width": 17, "height": 29 },
	{ "name": "walkUp4", "x": 279, "y": 335, "width": 17, "height": 29 },
	{ "name": "walkUp5", "x": 344, "y": 335, "width": 17, "height": 29 },
	{ "name": "walkUp0", "x": 25, "y": 336, "width": 14, "height": 29 },
	{ "name": "walkUp3", "x": 217, "y": 336, "width": 14, "height": 29 },
	{ "name": "runRight0", "x": 406, "y": 397, "width": 20, "height": 31 },
	{ "name": "runRight1", "x": 470, "y": 397, "width": 19, "height": 31 },
	{ "name": "walkRight0", "x": 25, "y": 399, "width": 14, "height": 29 },
	{ "name": "walkRight1", "x": 90, "y": 399, "width": 12, "height": 29 },
	{ "name": "walkRight3", "x": 218, "y": 399, "width": 14, "height": 29 },
	{ "name": "walkRight4", "x": 281, "y": 399, "width": 13, "height": 29 },
	{ "name": "walkRight2", "x": 153, "y": 400, "width": 16, "height": 28 },
	{ "name": "walkRight5", "x": 342, "y": 400, "width": 19, "height": 28 },
	{ "name": "runLeft0", "x": 406, "y": 461, "width": 20, "height": 31 },
	{ "name": "runLeft1", "x": 471, "y": 461, "width": 19, "height": 31 },
	{ "name": "walkLeft0", "x": 25, "y": 463, "width": 14, "height": 29 },
	{ "name": "walkLeft1", "x": 90, "y": 463, "width": 12, "height": 29 },
	{ "name": "walkLeft3", "x": 216, "y": 463, "width": 14, "height": 29 },
	{ "name": "walkLeft4", "x": 282, "y": 463, "width": 13, "height": 29 },
	{ "name": "walkLeft2", "x": 151, "y": 464, "width": 16, "height": 28 },
	{ "name": "walkLeft5", "x": 343, "y": 464, "width": 19, "height": 28 }
]
